api.py
gte.py
phi.py
phi_3_vision_mlx.py
phi_3_vision_mlx-0.1.5.dist-info/LICENSE
phi_3_vision_mlx-0.1.5.dist-info/METADATA
phi_3_vision_mlx-0.1.5.dist-info/WHEEL
phi_3_vision_mlx-0.1.5.dist-info/entry_points.txt
phi_3_vision_mlx-0.1.5.dist-info/top_level.txt
phi_3_vision_mlx-0.1.5.dist-info/RECORD
