Metadata-Version: 2.1
Name: phi-3-vision-mlx
Version: 0.1.5
Summary: Phi-3-Vision on Apple silicon with MLX
Home-page: https://github.com/JosefAlbers/Phi-3-Vision-MLX
Author: Josef Albers
Author-email: albersj66@gmail.com
License: MIT
Project-URL: Documentation, https://josefalbers.github.io/Phi-3-Vision-MLX/
Requires-Python: >=3.12.3
License-File: LICENSE
Requires-Dist: mlx ==0.15.0
Requires-Dist: transformers ==4.40.2
Requires-Dist: numpy ==1.26.4
Requires-Dist: matplotlib ==3.9.0
Requires-Dist: datasets ==2.19.1
Requires-Dist: gradio ==4.31.5
Requires-Dist: requests ==2.32.3
